repamatrix/__init__.py
repamatrix/matrix.py
repamatrix/webcam.py
repamatrix-0.0.2.dist-info/entry_points.txt
repamatrix-0.0.2.dist-info/LICENSE
repamatrix-0.0.2.dist-info/WHEEL
repamatrix-0.0.2.dist-info/METADATA
repamatrix-0.0.2.dist-info/RECORD
